pal/__init__.py
pal/cli.py
pal/db.py
pal/setup.py
pal/models/__init__.py
pal/models/entry.py
pal/utils/dates.py
pal/utils/interact.py
pal_log-0.0.1.dist-info/LICENSE
pal_log-0.0.1.dist-info/METADATA
pal_log-0.0.1.dist-info/WHEEL
pal_log-0.0.1.dist-info/entry_points.txt
pal_log-0.0.1.dist-info/top_level.txt
pal_log-0.0.1.dist-info/RECORD
