Metadata-Version: 2.1
Name: pal-log
Version: 0.0.1
Summary: Personal Activity Log
Author-email: Alvaro Clemente <clemente.varo@gmail.com>
License: MIT
Requires-Python: >=3.9
License-File: LICENSE
Requires-Dist: rich >=13.6.0
Provides-Extra: dev
Requires-Dist: black ; extra == 'dev'
Requires-Dist: build ; extra == 'dev'
Requires-Dist: flake8 ; extra == 'dev'
Requires-Dist: isort ; extra == 'dev'
Requires-Dist: mypy ; extra == 'dev'
Requires-Dist: pyls-isort ; extra == 'dev'
Requires-Dist: pylsp-mypy ; extra == 'dev'
Requires-Dist: pytest ; extra == 'dev'
Requires-Dist: python-lsp-black ; extra == 'dev'
Requires-Dist: python-lsp-server ; extra == 'dev'
Requires-Dist: twine ; extra == 'dev'
